export_to_telegraph/__init__.py
export_to_telegraph/article.py
export_to_telegraph/author.py
export_to_telegraph/common.py
export_to_telegraph/content.py
export_to_telegraph/domain.py
export_to_telegraph/final_touch.py
export_to_telegraph/images.py
export_to_telegraph/inner_article.py
export_to_telegraph/link.py
export_to_telegraph/offtopic.py
export_to_telegraph/tag_replace.py
export_to_telegraph/test.py
export_to_telegraph/title.py
export_to_telegraph-0.0.151.dist-info/LICENSE
export_to_telegraph-0.0.151.dist-info/METADATA
export_to_telegraph-0.0.151.dist-info/WHEEL
export_to_telegraph-0.0.151.dist-info/top_level.txt
export_to_telegraph-0.0.151.dist-info/RECORD
